sympytools/__init__.py
sympytools/jupyter.py
sympytools-0.0.1.dist-info/LICENSE
sympytools-0.0.1.dist-info/METADATA
sympytools-0.0.1.dist-info/WHEEL
sympytools-0.0.1.dist-info/top_level.txt
sympytools-0.0.1.dist-info/RECORD
