Metadata-Version: 2.1
Name: sympytools
Version: 0.0.1
Summary: Tools for using SymPy
Home-page: https://github.com/mathcube7/sympytools
Author: mathcube
Author-email: mathcube7@gmail.com
License: MIT
Platform: ALL
Classifier: Operating System :: OS Independent
Classifier: Programming Language :: Python :: 3
Requires-Python: >=3.6
License-File: LICENSE
Requires-Dist: sphinx
Requires-Dist: sympy
Requires-Dist: IPython
Requires-Dist: ipywidgets
Requires-Dist: clipboard
